MANIFEST.in
README.md
VERSION
requirements.txt
setup.cfg
setup.py
rhasspy_microphone_pyaudio_hermes.egg-info/PKG-INFO
rhasspy_microphone_pyaudio_hermes.egg-info/SOURCES.txt
rhasspy_microphone_pyaudio_hermes.egg-info/dependency_links.txt
rhasspy_microphone_pyaudio_hermes.egg-info/entry_points.txt
rhasspy_microphone_pyaudio_hermes.egg-info/requires.txt
rhasspy_microphone_pyaudio_hermes.egg-info/top_level.txt
rhasspymicrophone_pyaudio_hermes/__init__.py
rhasspymicrophone_pyaudio_hermes/__main__.py